[
	{
		"flavor": "",
		"hook": "",
		"importance": "",
		"localHookTemplate": "",
		"name": "vistasoft",
		"pathPlacement": "prepend",
		"subfolder": "",
		"toolboxRoot": "",
		"type": "git",
		"update": "",
		"url": "https://github.com/vistalab/vistasoft.git"
	},
	{
		"flavor": "",
		"hook": "",
		"name": "spm12",
		"pathPlacement": "append",
		"subfolder": "",
		"toolboxRoot": "",
		"type": "local",
		"update": "never",
		"url": "file://~/matlab/toolboxes/spm12"
	},
	{
		"flavor": "",
		"hook": "",
		"importance": "",
		"localHookTemplate": "",
		"name": "RemoteDataToolbox",
		"pathPlacement": "append",
		"subfolder": "",
		"toolboxRoot": "",
		"type": "git",
		"update": "",
		"url": "https://github.com/isetbio/RemoteDataToolbox.git"
	}
]
